rumbler/rumbler_test.py
rumbler/__init__.py
rumbler/rumbler.py
rumbler/LICENSE.txt
rumbler-0.123.457.dist-info/METADATA
rumbler-0.123.457.dist-info/entry_points.txt
rumbler-0.123.457.dist-info/WHEEL
rumbler-0.123.457.dist-info/top_level.txt
rumbler-0.123.457.dist-info/RECORD
rumbler-0.123.457.dist-info/DESCRIPTION.rst
rumbler-0.123.457.dist-info/metadata.json
