Metadata-Version: 2.0
Name: rumbler
Version: 0.123.457
Summary: Alias command from a yaml file 
Home-page: https://rumbler.readthedocs.org
Author: Rit Li
Author-email: rit@xap.me
License: MIT
Keywords: development yaml cli
Platform: UNKNOWN
Classifier: Development Status :: 4 - Beta
Classifier: Intended Audience :: Developers
Classifier: Topic :: Software Development :: Build Tools
Classifier: License :: OSI Approved :: MIT License
Classifier: Programming Language :: Python :: 2.7
Requires-Dist: PyYAML
Requires-Dist: tornado
Provides-Extra: dev
Requires-Dist: pytest; extra == 'dev'
